zmrobopi/GUI.py
zmrobopi/__init__.py
zmrobopi-0.0.3.dist-info/METADATA
zmrobopi-0.0.3.dist-info/WHEEL
zmrobopi-0.0.3.dist-info/license.txt
zmrobopi-0.0.3.dist-info/top_level.txt
zmrobopi-0.0.3.dist-info/RECORD
