Metadata-Version: 2.1
Name: zmrobopi
Version: 0.0.3
Summary: 控制QML Canvas绘图的库
Home-page: https://github.com/
Author: kimbell
Author-email: you@example.com
Classifier: Programming Language :: Python :: 3
Classifier: Operating System :: POSIX :: Linux
Requires-Python: >=3.6
License-File: license.txt
